cpsat_logutils/__init__.py
cpsat_logutils/parser.py
cpsat_logutils/blocks/__init__.py
cpsat_logutils/blocks/clauses_shared.py
cpsat_logutils/blocks/improving_bounds.py
cpsat_logutils/blocks/initial_model.py
cpsat_logutils/blocks/lns_stats.py
cpsat_logutils/blocks/log_block.py
cpsat_logutils/blocks/lp_cut.py
cpsat_logutils/blocks/lp_debug.py
cpsat_logutils/blocks/lp_dimension.py
cpsat_logutils/blocks/lp_pool.py
cpsat_logutils/blocks/lp_stats.py
cpsat_logutils/blocks/ls_stats.py
cpsat_logutils/blocks/objective_bounds.py
cpsat_logutils/blocks/preloading_model.py
cpsat_logutils/blocks/presolve_log.py
cpsat_logutils/blocks/presolve_summary.py
cpsat_logutils/blocks/presolved_model.py
cpsat_logutils/blocks/search_progress.py
cpsat_logutils/blocks/search_stats.py
cpsat_logutils/blocks/sequential_search_progress.py
cpsat_logutils/blocks/solution_repositories.py
cpsat_logutils/blocks/solutions.py
cpsat_logutils/blocks/solver.py
cpsat_logutils/blocks/solver_response.py
cpsat_logutils/blocks/tables.py
cpsat_logutils/blocks/task_timing.py
cpsat_logutils-0.0.3.dist-info/licenses/LICENSE
cpsat_logutils-0.0.3.dist-info/METADATA
cpsat_logutils-0.0.3.dist-info/WHEEL
cpsat_logutils-0.0.3.dist-info/top_level.txt
cpsat_logutils-0.0.3.dist-info/RECORD
