Metadata-Version: 2.4
Name: cpsat-logutils
Version: 0.0.3
Summary: Utils for parsing the logs of OR-Tools' CP-SAT solver.
Author-email: Dominik Krupke <krupked@gmail.com>
Classifier: Programming Language :: Python :: 3
Classifier: License :: OSI Approved :: MIT License
Classifier: Development Status :: 3 - Alpha
Requires-Python: >=3.10
License-File: LICENSE
Dynamic: license-file
